{
    "id": "com.linecorp.abc+kmm-shared-storage-android",
    "artifact_id": "kmm-shared-storage-android",
    "group_id": "com.linecorp.abc",
    "tag": "ios",
    "repos": [
        {
            "name": "Central",
            "base_url": "https://repo1.maven.org/maven2/",
            "versions": [
                {
                    "version": "1.0.1",
                    "usages": 0,
                    "date": "Nov 18, 2021",
                    "filetype": "aar",
                    "downloaded": true,
                    "applied_analyzes": []
                },
                {
                    "version": "1.0.2",
                    "usages": 0,
                    "date": "Nov 18, 2021",
                    "filetype": "aar",
                    "downloaded": true,
                    "applied_analyzes": []
                }
            ]
        }
    ]
}