{
    "id": "com.userleap+userleap-android-sdk",
    "artifact_id": "userleap-android-sdk",
    "group_id": "com.userleap",
    "tag": "sdk",
    "repos": [
        {
            "name": "Central",
            "base_url": "https://repo1.maven.org/maven2/",
            "versions": [
                {
                    "version": "2.2.1",
                    "usages": 0,
                    "date": "Aug 01, 2022",
                    "filetype": "aar",
                    "downloaded": true,
                    "applied_analyzes": []
                },
                {
                    "version": "2.2.2",
                    "usages": 0,
                    "date": "Aug 01, 2022",
                    "filetype": "aar",
                    "downloaded": true,
                    "applied_analyzes": []
                },
                {
                    "version": "2.2.3",
                    "usages": 0,
                    "date": "Aug 01, 2022",
                    "filetype": "",
                    "downloaded": false,
                    "applied_analyzes": []
                },
                {
                    "version": "2.3.0",
                    "usages": 0,
                    "date": "Aug 01, 2022",
                    "filetype": "",
                    "downloaded": false,
                    "applied_analyzes": []
                },
                {
                    "version": "2.3.1-alpha",
                    "usages": 0,
                    "date": "Aug 01, 2022",
                    "filetype": "",
                    "downloaded": false,
                    "applied_analyzes": []
                },
                {
                    "version": "2.4.0",
                    "usages": 0,
                    "date": "Aug 01, 2022",
                    "filetype": "",
                    "downloaded": false,
                    "applied_analyzes": []
                },
                {
                    "version": "2.4.1",
                    "usages": 0,
                    "date": "Aug 01, 2022",
                    "filetype": "",
                    "downloaded": false,
                    "applied_analyzes": []
                },
                {
                    "version": "2.5.0",
                    "usages": 0,
                    "date": "Aug 01, 2022",
                    "filetype": "",
                    "downloaded": false,
                    "applied_analyzes": []
                },
                {
                    "version": "2.5.1",
                    "usages": 0,
                    "date": "Aug 01, 2022",
                    "filetype": "",
                    "downloaded": false,
                    "applied_analyzes": []
                },
                {
                    "version": "2.5.2",
                    "usages": 0,
                    "date": "Aug 01, 2022",
                    "filetype": "",
                    "downloaded": false,
                    "applied_analyzes": []
                },
                {
                    "version": "2.5.3",
                    "usages": 0,
                    "date": "Aug 01, 2022",
                    "filetype": "",
                    "downloaded": false,
                    "applied_analyzes": []
                },
                {
                    "version": "2.6.0",
                    "usages": 0,
                    "date": "Aug 01, 2022",
                    "filetype": "",
                    "downloaded": false,
                    "applied_analyzes": []
                },
                {
                    "version": "2.6.1",
                    "usages": 0,
                    "date": "Aug 01, 2022",
                    "filetype": "",
                    "downloaded": false,
                    "applied_analyzes": []
                },
                {
                    "version": "2.6.2",
                    "usages": 0,
                    "date": "Aug 01, 2022",
                    "filetype": "",
                    "downloaded": false,
                    "applied_analyzes": []
                },
                {
                    "version": "2.6.3",
                    "usages": 0,
                    "date": "Aug 01, 2022",
                    "filetype": "",
                    "downloaded": false,
                    "applied_analyzes": []
                },
                {
                    "version": "2.6.4",
                    "usages": 0,
                    "date": "Aug 01, 2022",
                    "filetype": "",
                    "downloaded": false,
                    "applied_analyzes": []
                },
                {
                    "version": "2.6.5",
                    "usages": 0,
                    "date": "Aug 01, 2022",
                    "filetype": "",
                    "downloaded": false,
                    "applied_analyzes": []
                },
                {
                    "version": "2.6.6",
                    "usages": 0,
                    "date": "Aug 01, 2022",
                    "filetype": "",
                    "downloaded": false,
                    "applied_analyzes": []
                },
                {
                    "version": "2.6.7",
                    "usages": 0,
                    "date": "Aug 01, 2022",
                    "filetype": "",
                    "downloaded": false,
                    "applied_analyzes": []
                },
                {
                    "version": "2.6.8",
                    "usages": 0,
                    "date": "Aug 01, 2022",
                    "filetype": "aar",
                    "downloaded": true,
                    "applied_analyzes": []
                },
                {
                    "version": "2.6.9",
                    "usages": 0,
                    "date": "Aug 01, 2022",
                    "filetype": "aar",
                    "downloaded": true,
                    "applied_analyzes": []
                }
            ]
        }
    ]
}