{
    "id": "com.netease.nimlib.flutter+nrtc",
    "artifact_id": "nrtc",
    "group_id": "com.netease.nimlib.flutter",
    "tag": "networking",
    "repos": [
        {
            "name": "Central",
            "base_url": "https://repo1.maven.org/maven2/",
            "versions": [
                {
                    "version": "8.11.11",
                    "usages": 2,
                    "date": "Sep 02, 2021",
                    "filetype": "aar",
                    "downloaded": true,
                    "applied_analyzes": []
                },
                {
                    "version": "8.11.12",
                    "usages": 2,
                    "date": "Sep 02, 2021",
                    "filetype": "aar",
                    "downloaded": true,
                    "applied_analyzes": []
                },
                {
                    "version": "8.11.7",
                    "usages": 2,
                    "date": "Sep 02, 2021",
                    "filetype": "",
                    "downloaded": false,
                    "applied_analyzes": []
                },
                {
                    "version": "8.11.9",
                    "usages": 2,
                    "date": "Sep 02, 2021",
                    "filetype": "",
                    "downloaded": false,
                    "applied_analyzes": []
                },
                {
                    "version": "8.6.3",
                    "usages": 2,
                    "date": "Sep 02, 2021",
                    "filetype": "aar",
                    "downloaded": true,
                    "applied_analyzes": []
                },
                {
                    "version": "8.6.5",
                    "usages": 2,
                    "date": "Sep 02, 2021",
                    "filetype": "aar",
                    "downloaded": true,
                    "applied_analyzes": []
                }
            ]
        }
    ]
}