{
    "id": "io.github.woody230+ktx-intent-android-debug",
    "artifact_id": "ktx-intent-android-debug",
    "group_id": "io.github.woody230",
    "tag": "intent",
    "repos": [
        {
            "name": "Central",
            "base_url": "https://repo1.maven.org/maven2/",
            "versions": [
                {
                    "version": "4.0.1",
                    "usages": 2,
                    "date": "Jun 19, 2022",
                    "filetype": "aar",
                    "downloaded": true,
                    "applied_analyzes": []
                }
            ]
        }
    ]
}