{
    "id": "io.github.acelost+pojson-native-json",
    "artifact_id": "pojson-native-json",
    "group_id": "io.github.acelost",
    "tag": "json",
    "repos": [
        {
            "name": "Central",
            "base_url": "https://repo1.maven.org/maven2/",
            "versions": [
                {
                    "version": "0.0.3",
                    "usages": 0,
                    "date": "May 13, 2021",
                    "filetype": "",
                    "downloaded": false,
                    "applied_analyzes": []
                },
                {
                    "version": "0.0.4",
                    "usages": 0,
                    "date": "May 13, 2021",
                    "filetype": "",
                    "downloaded": false,
                    "applied_analyzes": []
                },
                {
                    "version": "0.0.5",
                    "usages": 0,
                    "date": "May 13, 2021",
                    "filetype": "",
                    "downloaded": false,
                    "applied_analyzes": []
                }
            ]
        }
    ]
}