{
    "id": "com.example.ivanyuliyanov.icardtask.phonebook+mylibrary",
    "artifact_id": "mylibrary",
    "group_id": "com.example.ivanyuliyanov.icardtask.phonebook",
    "tag": "example",
    "repos": [
        {
            "name": "Gradle Releases",
            "base_url": "https://repo.gradle.org/gradle/libs-releases/",
            "versions": [
                {
                    "version": "1.0.0",
                    "usages": 0,
                    "date": "Mar 13, 2019",
                    "filetype": "aar",
                    "downloaded": true,
                    "applied_analyzes": []
                }
            ]
        },
        {
            "name": "Liferay Public",
            "base_url": "https://repository.liferay.com/nexus/content/repositories/public/",
            "versions": [
                {
                    "version": "1.0.0",
                    "usages": 0,
                    "date": "Mar 13, 2019",
                    "filetype": "",
                    "downloaded": false,
                    "applied_analyzes": []
                }
            ]
        },
        {
            "name": "AutonomX",
            "base_url": "http://artifact.autonomx.io/artifactory/libs-release/",
            "versions": [
                {
                    "version": "1.0.0",
                    "usages": 0,
                    "date": "Mar 13, 2019",
                    "filetype": "",
                    "downloaded": false,
                    "applied_analyzes": []
                }
            ]
        }
    ]
}