{
    "id": "net.take+blip-chat",
    "artifact_id": "blip-chat",
    "group_id": "net.take",
    "tag": "widget",
    "repos": [
        {
            "name": "Central",
            "base_url": "https://repo1.maven.org/maven2/",
            "versions": [
                {
                    "version": "0.0.26",
                    "usages": 0,
                    "date": "Apr 10, 2019",
                    "filetype": "",
                    "downloaded": false,
                    "applied_analyzes": []
                },
                {
                    "version": "2.1.12",
                    "usages": 0,
                    "date": "Apr 10, 2019",
                    "filetype": "",
                    "downloaded": false,
                    "applied_analyzes": []
                }
            ]
        }
    ]
}