{
    "id": "com.unity3d.ads+unity-ads",
    "artifact_id": "unity-ads",
    "group_id": "com.unity3d.ads",
    "tag": "video",
    "repos": [
        {
            "name": "Central",
            "base_url": "https://repo1.maven.org/maven2/",
            "versions": [
                {
                    "version": "3.7.1",
                    "usages": 6,
                    "date": "Aug 06, 2020",
                    "filetype": "",
                    "downloaded": false,
                    "applied_analyzes": []
                },
                {
                    "version": "3.7.2",
                    "usages": 6,
                    "date": "Aug 06, 2020",
                    "filetype": "",
                    "downloaded": false,
                    "applied_analyzes": []
                },
                {
                    "version": "3.7.4",
                    "usages": 6,
                    "date": "Aug 06, 2020",
                    "filetype": "",
                    "downloaded": false,
                    "applied_analyzes": []
                },
                {
                    "version": "3.7.5",
                    "usages": 6,
                    "date": "Aug 06, 2020",
                    "filetype": "",
                    "downloaded": false,
                    "applied_analyzes": []
                },
                {
                    "version": "4.0.0",
                    "usages": 6,
                    "date": "Aug 06, 2020",
                    "filetype": "",
                    "downloaded": false,
                    "applied_analyzes": []
                },
                {
                    "version": "4.0.1",
                    "usages": 6,
                    "date": "Aug 06, 2020",
                    "filetype": "",
                    "downloaded": false,
                    "applied_analyzes": []
                },
                {
                    "version": "4.1.0",
                    "usages": 6,
                    "date": "Aug 06, 2020",
                    "filetype": "",
                    "downloaded": false,
                    "applied_analyzes": []
                },
                {
                    "version": "4.2.0",
                    "usages": 6,
                    "date": "Aug 06, 2020",
                    "filetype": "",
                    "downloaded": false,
                    "applied_analyzes": []
                },
                {
                    "version": "4.2.1",
                    "usages": 6,
                    "date": "Aug 06, 2020",
                    "filetype": "",
                    "downloaded": false,
                    "applied_analyzes": []
                },
                {
                    "version": "4.3.0",
                    "usages": 6,
                    "date": "Aug 06, 2020",
                    "filetype": "",
                    "downloaded": false,
                    "applied_analyzes": []
                }
            ]
        }
    ]
}