{
    "id": "com.lukekorth+EzLoaders",
    "artifact_id": "EzLoaders",
    "group_id": "com.lukekorth",
    "tag": "loader",
    "repos": [
        {
            "name": "Central",
            "base_url": "https://repo1.maven.org/maven2/",
            "versions": [
                {
                    "version": "1.1",
                    "usages": 0,
                    "date": "May 23, 2014",
                    "filetype": "aar",
                    "downloaded": true,
                    "applied_analyzes": []
                }
            ]
        }
    ]
}